pulp_2_tests/__init__.py
pulp_2_tests/constants.py
pulp_2_tests/tests/__init__.py
pulp_2_tests/tests/docker/__init__.py
pulp_2_tests/tests/docker/utils.py
pulp_2_tests/tests/docker/api_v2/__init__.py
pulp_2_tests/tests/docker/api_v2/test_copy.py
pulp_2_tests/tests/docker/api_v2/test_crud.py
pulp_2_tests/tests/docker/api_v2/test_duplicate_uploads.py
pulp_2_tests/tests/docker/api_v2/test_sync.py
pulp_2_tests/tests/docker/api_v2/test_sync_publish.py
pulp_2_tests/tests/docker/api_v2/test_tags.py
pulp_2_tests/tests/docker/api_v2/test_upload.py
pulp_2_tests/tests/docker/api_v2/utils.py
pulp_2_tests/tests/docker/cli/__init__.py
pulp_2_tests/tests/docker/cli/test_crud.py
pulp_2_tests/tests/docker/cli/test_sync_publish.py
pulp_2_tests/tests/docker/cli/utils.py
pulp_2_tests/tests/ostree/__init__.py
pulp_2_tests/tests/ostree/utils.py
pulp_2_tests/tests/ostree/api_v2/__init__.py
pulp_2_tests/tests/ostree/api_v2/test_copy.py
pulp_2_tests/tests/ostree/api_v2/test_crud.py
pulp_2_tests/tests/ostree/api_v2/test_publish.py
pulp_2_tests/tests/ostree/api_v2/test_sync.py
pulp_2_tests/tests/platform/__init__.py
pulp_2_tests/tests/platform/utils.py
pulp_2_tests/tests/platform/api_v2/__init__.py
pulp_2_tests/tests/platform/api_v2/test_consumer.py
pulp_2_tests/tests/platform/api_v2/test_content_applicability.py
pulp_2_tests/tests/platform/api_v2/test_login.py
pulp_2_tests/tests/platform/api_v2/test_repository.py
pulp_2_tests/tests/platform/api_v2/test_search.py
pulp_2_tests/tests/platform/api_v2/test_user.py
pulp_2_tests/tests/platform/api_v2/utils.py
pulp_2_tests/tests/platform/cli/__init__.py
pulp_2_tests/tests/platform/cli/test_pulp_manage_db.py
pulp_2_tests/tests/platform/cli/test_selinux.py
pulp_2_tests/tests/puppet/__init__.py
pulp_2_tests/tests/puppet/utils.py
pulp_2_tests/tests/puppet/api_v2/__init__.py
pulp_2_tests/tests/puppet/api_v2/test_crud.py
pulp_2_tests/tests/puppet/api_v2/test_duplicate_uploads.py
pulp_2_tests-2018.11.1.dist-info/DESCRIPTION.rst
pulp_2_tests-2018.11.1.dist-info/METADATA
pulp_2_tests-2018.11.1.dist-info/RECORD
pulp_2_tests-2018.11.1.dist-info/WHEEL
pulp_2_tests-2018.11.1.dist-info/metadata.json
pulp_2_tests-2018.11.1.dist-info/top_level.txt
