Metadata-Version: 2.0
Name: pulp-2-tests
Version: 2018.11.1
Summary: Functional tests for Pulp 2
Home-page: https://github.com/PulpQE/pulp-2-tests
Author: Jeremy Audet
Author-email: ichimonji10@gmail.com
License: GPLv3
Platform: UNKNOWN
Classifier: Development Status :: 1 - Planning
Classifier: Intended Audience :: Developers
Classifier: License :: OSI Approved :: GNU General Public License v3 or later (GPLv3+)
Classifier: Programming Language :: Python :: 3.4
Classifier: Programming Language :: Python :: 3.5
Classifier: Programming Language :: Python :: 3.6
Classifier: Programming Language :: Python :: 3.7
Provides-Extra: dev
Requires-Dist: jsonschema
Requires-Dist: packaging
Requires-Dist: pulp-smash (<1!1,>=1!0.0.1)
Requires-Dist: python-dateutil
Provides-Extra: dev
Requires-Dist: flake8; extra == 'dev'
Requires-Dist: flake8-docstrings; extra == 'dev'
Requires-Dist: flake8-quotes; extra == 'dev'
Requires-Dist: pydocstyle; extra == 'dev'
Requires-Dist: pylint; extra == 'dev'
Requires-Dist: sphinx; extra == 'dev'
Requires-Dist: wheel; extra == 'dev'
Requires-Dist: twine; extra == 'dev'
